<?xml version="1.0" encoding="utf-16"?>
<Variable xmlns:xsi="http://www.w3.org/2001/XMLSchema-instance" xmlns:xsd="http://www.w3.org/2001/XMLSchema" xsi:type="ScsVehicleVariable">
  <ChildVariables />
  <Id>fbf3ef30-2e80-4c82-a527-fc8397763a55</Id>
  <IsEnabled>false</IsEnabled>
  <AccessoryItems />
  <Game>ATS</Game>
  <InternalName>pete.jc</InternalName>
  <VehicleAuthor>jon-ruda</VehicleAuthor>
  <VehicleImage />
  <VehicleName>Pete|389/379</VehicleName>
  <VehicleType>OldTrucks</VehicleType>
  <VehicleVariants>
    <Variant>
      <InternalName>36.pete.jc.cabin</InternalName>
      <Name>389 36` Flattop</Name>
    </Variant>
    <Variant>
      <InternalName>36_379.pete.jc.cabin</InternalName>
      <Name>379 36` Flattop</Name>
    </Variant>
    <Variant>
      <InternalName>3686.pete.jc.cabin</InternalName>
      <Name>389 36` Flattop</Name>
    </Variant>
    <Variant>
      <InternalName>3686_379.pete.jc.cabin</InternalName>
      <Name>379 36` Flattop</Name>
    </Variant>
    <Variant>
      <InternalName>36l.pete.jc.cabin</InternalName>
      <Name>389 36` Flattop</Name>
    </Variant>
    <Variant>
      <InternalName>36l_379.pete.jc.cabin</InternalName>
      <Name>379 36` Flattop</Name>
    </Variant>
    <Variant>
      <InternalName>48.pete.jc.cabin</InternalName>
      <Name>389 48` Flattop</Name>
    </Variant>
    <Variant>
      <InternalName>48_379.pete.jc.cabin</InternalName>
      <Name>379 48` Flattop</Name>
    </Variant>
    <Variant>
      <InternalName>4886.pete.jc.cabin</InternalName>
      <Name>389 48` Flattop</Name>
    </Variant>
    <Variant>
      <InternalName>4886_379.pete.jc.cabin</InternalName>
      <Name>379 48` Flattop</Name>
    </Variant>
    <Variant>
      <InternalName>48l.pete.jc.cabin</InternalName>
      <Name>389 48` Flattop</Name>
    </Variant>
    <Variant>
      <InternalName>48l_379.pete.jc.cabin</InternalName>
      <Name>379 48` Flattop</Name>
    </Variant>
    <Variant>
      <InternalName>daycab.pete.jc.cabin</InternalName>
      <Name>389 Daycab</Name>
    </Variant>
    <Variant>
      <InternalName>daycab_379.pete.jc.cabin</InternalName>
      <Name>379 Daycab</Name>
    </Variant>
    <Variant>
      <InternalName>daycab86.pete.jc.cabin</InternalName>
      <Name>389 Daycab</Name>
    </Variant>
    <Variant>
      <InternalName>daycab86_379.pete.jc.cabin</InternalName>
      <Name>379 Daycab</Name>
    </Variant>
    <Variant>
      <InternalName>daycabd.pete.jc.cabin</InternalName>
      <Name>389 Daycab</Name>
    </Variant>
    <Variant>
      <InternalName>daycabd_379.pete.jc.cabin</InternalName>
      <Name>379 Daycab</Name>
    </Variant>
    <Variant>
      <InternalName>daycabl.pete.jc.cabin</InternalName>
      <Name>389 Daycab</Name>
    </Variant>
    <Variant>
      <InternalName>daycabl_379.pete.jc.cabin</InternalName>
      <Name>379 Daycab</Name>
    </Variant>
    <Variant>
      <InternalName>flattop.pete.jc.cabin</InternalName>
      <Name>389 72` Flattop</Name>
    </Variant>
    <Variant>
      <InternalName>flattop_379.pete.jc.cabin</InternalName>
      <Name>379 63` Flattop</Name>
    </Variant>
    <Variant>
      <InternalName>flattop86.pete.jc.cabin</InternalName>
      <Name>389 72` Flattop</Name>
    </Variant>
    <Variant>
      <InternalName>flat86_379.pete.jc.cabin</InternalName>
      <Name>379 63` Flattop</Name>
    </Variant>
    <Variant>
      <InternalName>flattopl.pete.jc.cabin</InternalName>
      <Name>389 72` Flattop</Name>
    </Variant>
    <Variant>
      <InternalName>flatl_379.pete.jc.cabin</InternalName>
      <Name>379 63` Flattop</Name>
    </Variant>
    <Variant>
      <InternalName>highroof.pete.jc.cabin</InternalName>
      <Name>389 72` High Roof</Name>
    </Variant>
    <Variant>
      <InternalName>highroof_379.pete.jc.cabin</InternalName>
      <Name>379 63` High Roof</Name>
    </Variant>
    <Variant>
      <InternalName>highroof86.pete.jc.cabin</InternalName>
      <Name>389 72` High Roof</Name>
    </Variant>
    <Variant>
      <InternalName>hroof86_379.pete.jc.cabin</InternalName>
      <Name>379 63` High Roof</Name>
    </Variant>
    <Variant>
      <InternalName>highroofl.pete.jc.cabin</InternalName>
      <Name>389 72` High Roof</Name>
    </Variant>
    <Variant>
      <InternalName>hroofl_379.pete.jc.cabin</InternalName>
      <Name>379 63` High Roof</Name>
    </Variant>
  </VehicleVariants>
</Variable>
