<?xml version="1.0" encoding="utf-16"?>
<Variable xmlns:xsi="http://www.w3.org/2001/XMLSchema-instance" xmlns:xsd="http://www.w3.org/2001/XMLSchema" xsi:type="ScsVehicleVariable">
  <ChildVariables />
  <IsEnabled>true</IsEnabled>
  <Validators />
  <AccessoryItems />
  <FilePath>C:\Users\shawh\Documents\Mods Studio 2\UserVehicles\850 Modding\ATS.edison.bde.xml</FilePath>
  <Game>ATS</Game>
  <InternalName>edison.bde</InternalName>
  <SoundItems />
  <VehicleAuthor>850 Modding</VehicleAuthor>
  <VehicleName>850 Modding|Edison Motors BDE Wrecker</VehicleName>
  <VehicleType>OldTrucks</VehicleType>
  <VehicleVariants>
    <Variant>
      <AccessoryDependencies />
      <InternalName>daycab.edison.bde.cabin</InternalName>
      <Name>Daycab</Name>
    </Variant>
    <Variant>
      <AccessoryDependencies />
      <InternalName>sleeper01.edison.bde.cabin</InternalName>
      <Name>Flattop</Name>
    </Variant>
  </VehicleVariants>
  <XmlDefinitionAuthor>Dr.PupzEditz.scs, Pauly, 850 Modding</XmlDefinitionAuthor>
  <DateUpdated xsi:nil="true" />
</Variable>